texteditpad
