Metadata-Version: 1.1
Name: texteditpad
Version: 0.31
Summary: Simple textbox editing widget with Emacs-like keybindings
Home-page: https://github.com/yskmt/texteditpad
Author: Yusuke Sakamoto
Author-email: yus.sakamoto@gmail.com
License: MIT
Keywords: curses terminal text edit box pad
Platform: UNKNOWN
Classifier: Intended Audience :: End Users/Desktop
Classifier: Environment :: Console :: Curses
Classifier: Operating System :: MacOS :: MacOS X
Classifier: Operating System :: POSIX
Classifier: Natural Language :: English
Classifier: Programming Language :: Python :: 2.7
Classifier: Topic :: Terminals
Classifier: Topic :: Utilities
Classifier: Topic :: Text Editors
